eigenda/__init__.py
eigenda/_version.py
eigenda/client.py
eigenda/client_v2.py
eigenda/client_v2_full.py
eigenda/config.py
eigenda/payment.py
eigenda/py.typed
eigenda/retriever.py
eigenda/auth/__init__.py
eigenda/auth/signer.py
eigenda/codec/__init__.py
eigenda/codec/blob_codec.py
eigenda/core/__init__.py
eigenda/core/types.py
eigenda/grpc/__init__.py
eigenda/grpc/churner/churner_pb2.py
eigenda/grpc/churner/churner_pb2_grpc.py
eigenda/grpc/common/common_pb2.py
eigenda/grpc/common/common_pb2_grpc.py
eigenda/grpc/common/v2/common_v2_pb2.py
eigenda/grpc/common/v2/common_v2_pb2_grpc.py
eigenda/grpc/disperser/disperser_pb2.py
eigenda/grpc/disperser/disperser_pb2_grpc.py
eigenda/grpc/disperser/v2/disperser_v2_pb2.py
eigenda/grpc/disperser/v2/disperser_v2_pb2_grpc.py
eigenda/grpc/encoder/encoder_pb2.py
eigenda/grpc/encoder/encoder_pb2_grpc.py
eigenda/grpc/encoder/v2/encoder_v2_pb2.py
eigenda/grpc/encoder/v2/encoder_v2_pb2_grpc.py
eigenda/grpc/node/node_pb2.py
eigenda/grpc/node/node_pb2_grpc.py
eigenda/grpc/relay/relay_pb2.py
eigenda/grpc/relay/relay_pb2_grpc.py
eigenda/grpc/retriever/retriever_pb2.py
eigenda/grpc/retriever/retriever_pb2_grpc.py
eigenda/grpc/retriever/v2/retriever_v2_pb2.py
eigenda/grpc/retriever/v2/retriever_v2_pb2_grpc.py
eigenda/grpc/validator/node_v2_pb2.py
eigenda/grpc/validator/node_v2_pb2_grpc.py
eigenda/utils/__init__.py
eigenda/utils/abi_encoding.py
eigenda/utils/bn254_field.py
eigenda/utils/fp2_arithmetic.py
eigenda/utils/g2_decompression.py
eigenda/utils/gnark_decompression.py
eigenda/utils/serialization.py
powerloom_eigenda-0.1.0.dist-info/METADATA
powerloom_eigenda-0.1.0.dist-info/WHEEL
powerloom_eigenda-0.1.0.dist-info/licenses/LICENSE
powerloom_eigenda-0.1.0.dist-info/RECORD
