Metadata-Version: 2.4
Name: powerloom-eigenda
Version: 0.1.0
Summary: Unofficial Python client for EigenDA v2 - a decentralized data availability (DA) service. This implementation is maintained by the Powerloom team.
Project-URL: Homepage, https://powerloom.io
Project-URL: Repository, https://github.com/powerloom/eigenda-py
Project-URL: Documentation, https://github.com/powerloom/eigenda-py/blob/master/docs/getting-started.md
Project-URL: Bug Tracker, https://github.com/powerloom/eigenda-py/issues
Project-URL: EigenDA, https://www.eigenda.xyz/
Author-email: Swaroop Hegde <email@swaroophegde.com>
Maintainer-email: Powerloom Team <hello@powerloom.io>
License: MIT
License-File: LICENSE
Keywords: blockchain,data-availability,eigenda,ethereum,powerloom,web3
Classifier: Development Status :: 4 - Beta
Classifier: Intended Audience :: Developers
Classifier: License :: OSI Approved :: MIT License
Classifier: Programming Language :: Python :: 3
Classifier: Programming Language :: Python :: 3.9
Classifier: Programming Language :: Python :: 3.10
Classifier: Programming Language :: Python :: 3.11
Classifier: Programming Language :: Python :: 3.12
Classifier: Programming Language :: Python :: 3.13
Classifier: Topic :: Internet :: WWW/HTTP
Classifier: Topic :: Software Development :: Libraries :: Python Modules
Classifier: Topic :: System :: Distributed Computing
Requires-Python: <3.14,>=3.9
Requires-Dist: cryptography>=41.0.0
Requires-Dist: eth-abi>=4.0.0
Requires-Dist: eth-account>=0.10.0
Requires-Dist: eth-typing>=3.0.0
Requires-Dist: eth-utils>=2.0.0
Requires-Dist: grpcio-tools>=1.60.0
Requires-Dist: grpcio>=1.60.0
Requires-Dist: protobuf>=4.25.0
Requires-Dist: pycryptodome>=3.19.0
Requires-Dist: python-dotenv>=1.0.0
Requires-Dist: web3>=6.0.0
Provides-Extra: dev
Requires-Dist: black>=23.0.0; extra == 'dev'
Requires-Dist: flake8>=6.0.0; extra == 'dev'
Requires-Dist: isort>=5.12.0; extra == 'dev'
Requires-Dist: mypy>=1.5.0; extra == 'dev'
Requires-Dist: pre-commit>=3.0.0; extra == 'dev'
Requires-Dist: pylint>=3.0.0; extra == 'dev'
Requires-Dist: pytest-asyncio>=0.21.0; extra == 'dev'
Requires-Dist: pytest-cov>=4.0.0; extra == 'dev'
Requires-Dist: pytest-mock>=3.10.0; extra == 'dev'
Requires-Dist: pytest>=7.0.0; extra == 'dev'
Requires-Dist: types-protobuf>=4.24.0; extra == 'dev'
Requires-Dist: types-requests>=2.31.0; extra == 'dev'
Provides-Extra: docs
Requires-Dist: autodoc-pydantic>=2.0.0; extra == 'docs'
Requires-Dist: sphinx-rtd-theme>=2.0.0; extra == 'docs'
Requires-Dist: sphinx>=7.0.0; extra == 'docs'
Provides-Extra: notebook
Requires-Dist: ipython>=8.0.0; extra == 'notebook'
Requires-Dist: jupyter>=1.0.0; extra == 'notebook'
